tests/__init__.py
tests/test_download_spectra.py
tests/test_properties.py
tests/test_search.py
wiserep_api/__init__.py
wiserep_api/_version.py
wiserep_api/api.py
wiserep_api/properties.py
wiserep_api/search.py
wiserep_api/snid.py
wiserep_api/spectra.py
wiserep_api/static/spectral_types.json
wiserep_api-0.1.10.dist-info/licenses/LICENSE
wiserep_api-0.1.10.dist-info/METADATA
wiserep_api-0.1.10.dist-info/WHEEL
wiserep_api-0.1.10.dist-info/top_level.txt
wiserep_api-0.1.10.dist-info/RECORD
