Metadata-Version: 2.4
Name: wiserep_api
Version: 0.1.10
Summary: API to access WiserRep data from command lines
Home-page: https://github.com/temuller/wiserep_api
Author: Tomás Enrique Müller-Bravo
Author-email: t.e.muller-bravo@ice.csic.es
License: MIT
Classifier: Programming Language :: Python :: 3
Classifier: License :: OSI Approved :: MIT License
Classifier: Operating System :: OS Independent
Requires-Python: >=3.9
License-File: LICENSE
Requires-Dist: numpy
Requires-Dist: pandas
Requires-Dist: astropy
Requires-Dist: requests
Requires-Dist: lxml
Dynamic: author
Dynamic: author-email
Dynamic: classifier
Dynamic: description
Dynamic: description-content-type
Dynamic: home-page
Dynamic: license
Dynamic: license-file
Dynamic: requires-dist
Dynamic: requires-python
Dynamic: summary
